pyxora/__init__.py
pyxora/__main__.py
pyxora/assets.py
pyxora/camera.py
pyxora/display.py
pyxora/objects.py
pyxora/scene.py
pyxora/script.py
pyxora/data/images/icon.png
pyxora/data/images/logo.png
pyxora/data/template/main.py
pyxora/data/template/scenes/game.py
pyxora/docs/__init__.py
pyxora/docs/build.py
pyxora/docs/local.py
pyxora/docs/online.py
pyxora/editor/__init__.py
pyxora/editor/app.py
pyxora/editor/constants.py
pyxora/editor/input.py
pyxora/editor/runtime.py
pyxora/editor/ui/__init__.py
pyxora/editor/ui/code_editor.py
pyxora/editor/ui/console.py
pyxora/editor/ui/controls.py
pyxora/editor/ui/explorer.py
pyxora/editor/ui/preview.py
pyxora/editor/ui/window.py
pyxora/editor/ui/workspace.py
pyxora/projects/__init__.py
pyxora/projects/build.py
pyxora/projects/delete.py
pyxora/projects/explore.py
pyxora/projects/format.py
pyxora/projects/info.py
pyxora/projects/list.py
pyxora/projects/new.py
pyxora/projects/path.py
pyxora/projects/rename.py
pyxora/projects/run.py
pyxora/utils/__init__.py
pyxora/utils/asyncio.py
pyxora/utils/decorators.py
pyxora/utils/engine.py
pyxora/utils/platform.py
pyxora/utils/python.py
pyxora/wrapper/__init__.py
pyxora/wrapper/functions.py
pyxora/wrapper/image.py
pyxora/wrapper/music.py
pyxora/wrapper/sfx.py
pyxora/wrapper/shapes.py
pyxora/wrapper/text.py
pyxora-0.7.1.dist-info/licenses/LICENSE.txt
pyxora-0.7.1.dist-info/METADATA
pyxora-0.7.1.dist-info/WHEEL
pyxora-0.7.1.dist-info/entry_points.txt
pyxora-0.7.1.dist-info/top_level.txt
pyxora-0.7.1.dist-info/RECORD
