Metadata-Version: 2.4
Name: pyxora
Version: 0.7.1
Summary: A game engine library using pygame-ce, pymunk, and more
Author-email: AntonisDevStuff <contact@antonisdevstuff.com>
License-Expression: MIT
Project-URL: Homepage, https://pyxora.github.io/pyxora-website
Project-URL: Documentation, https://pyxora.github.io/pyxora-docs
Project-URL: Repository, https://github.com/pyxora/pyxora
Project-URL: Issues, https://github.com/pyxora/pyxora/issues
Project-URL: Releases, https://github.com/pyxora/pyxora/releases
Keywords: engine,game engine,game development
Classifier: Development Status :: 4 - Beta
Classifier: Operating System :: Microsoft :: Windows
Classifier: Operating System :: POSIX :: Linux
Classifier: Operating System :: MacOS
Classifier: Programming Language :: Python :: 3
Classifier: Topic :: Software Development :: Libraries :: pygame
Requires-Python: >=3.11
License-File: LICENSE.txt
Requires-Dist: pygame-ce==2.5.6
Requires-Dist: pymunk==7.2.0
Requires-Dist: pdoc==16.0.0
Requires-Dist: cx_Freeze==8.4.1
Requires-Dist: pygbag==0.9.2
Requires-Dist: pillow==12.0.0
Dynamic: license-file
